percepthor/__init__.py
percepthor/auth.py
percepthor/lib.py
percepthor/permissions.py
percepthor/routes.py
percepthor/service.py
percepthor/validation.py
percepthor/version.py
percepthor-0.6.3.dist-info/METADATA
percepthor-0.6.3.dist-info/WHEEL
percepthor-0.6.3.dist-info/top_level.txt
percepthor-0.6.3.dist-info/RECORD
