Metadata-Version: 2.4
Name: percepthor
Version: 0.6.3
Summary: Common Percepthor Development Module
Author: Erick Salas
Author-email: erick.salas@ermiry.com
Classifier: Programming Language :: Python :: 3
Classifier: License :: OSI Approved :: MIT License
Classifier: Operating System :: OS Independent
Requires-Python: >=3.6
